{
    "PortfolioModalItmes": [
        {
            "id": "portfolioModal1",
            "codeItem": "buso1",
            "image": "img/portfolio/jacket1.jpg"
        },
        {
            "id": "portfolioModal2",
            "codeItem": "buso2",
            "image": "img/portfolio/jeans1.jpg"
        },
        {
            "id": "portfolioModal3",
            "codeItem": "buso1",
            "image": "img/portfolio/buso1.jpg"
        },
        {
            "id": "portfolioModal4",
            "codeItem": "buso2",
            "image": "img/portfolio/buso2.jpg"
        },
        {
            "id": "portfolioModal5",
            "codeItem": "buso3",
            "image": "img/portfolio/buso3.jpg"
        },
        {
            "id": "portfolioModal6",
            "codeItem": "jeandama1-1",
            "image": "img/portfolio/jeandama1-1.jpg"
        },
        {
            "id": "portfolioModal7",
            "codeItem": "buso4",
            "image": "img/portfolio/buso4.jpg"
        },
        {
            "id": "portfolioModal8",
            "codeItem": "buso5",
            "image": "img/portfolio/buso5.jpg"
        },
        {
            "id": "portfolioModal9",
            "codeItem": "buso6",
            "image": "img/portfolio/buso6.jpg"
        }
    ]
}